fnnlsEigen.cp37-win_amd64.pyd
test/__init__.py
test/test_fnnls.py
fnnlsEigen-1.0.1.dist-info/LICENSE
fnnlsEigen-1.0.1.dist-info/METADATA
fnnlsEigen-1.0.1.dist-info/WHEEL
fnnlsEigen-1.0.1.dist-info/top_level.txt
fnnlsEigen-1.0.1.dist-info/RECORD
