Metadata-Version: 2.1
Name: fnnlsEigen
Version: 1.0.1
Summary: A fast nnls solver for python implemented in C++ using Eigen
Home-page: https://github.com/mikaeltw/fnnlsEigen
Author: Mikael Twengström
Author-email: m.twengstrom@gmail.com
License: MIT
Platform: Linux
Platform: Windows
Classifier: Programming Language :: Python :: 3
Classifier: Programming Language :: Python :: 3.7
Classifier: Programming Language :: Python :: 3.8
Classifier: Programming Language :: Python :: 3.9
Classifier: License :: OSI Approved :: MIT License
Classifier: Operating System :: POSIX :: Linux
Classifier: Operating System :: Microsoft :: Windows :: Windows 10
Requires-Python: >=3.7.8
License-File: LICENSE
